fridge/_version.py
fridge/application.py
fridge/flags.py
fridge/ioc.py
ls336_ioc-0.1.1.dist-info/LICENSE.md
ls336_ioc-0.1.1.dist-info/METADATA
ls336_ioc-0.1.1.dist-info/WHEEL
ls336_ioc-0.1.1.dist-info/entry_points.txt
ls336_ioc-0.1.1.dist-info/top_level.txt
ls336_ioc-0.1.1.dist-info/RECORD
