Metadata-Version: 2.1
Name: ls336-ioc
Version: 0.1.1
Summary: CAproto-based pure-Python EPICS IOC for the Lakeshore 336 temperature controller
Author-email: Matthias Rössle <matthias.roessle@helmholtz-berlin.de>, Florin Boariu <florin.pt@rootshell.ro>
Classifier: Programming Language :: Python :: 3
Classifier: License :: OSI Approved :: GNU General Public License v3 or later (GPLv3+)
Classifier: Operating System :: POSIX :: Linux
Classifier: Development Status :: 2 - Pre-Alpha
Classifier: Environment :: Console
Classifier: Intended Audience :: Science/Research
Classifier: Topic :: Scientific/Engineering
Requires-Python: >=3.8
License-File: LICENSE.md
Requires-Dist: caproto
Requires-Dist: emmi >=0.1.3
Requires-Dist: pyvisa
Requires-Dist: pyvisa-py
Requires-Dist: parse
Provides-Extra: test
Requires-Dist: pytest ; extra == 'test'
Requires-Dist: pytest-cov ; extra == 'test'
